streamlit_cytoscape/__init__.py
streamlit_cytoscape/component.py
streamlit_cytoscape/events.py
streamlit_cytoscape/frontend/.gitignore
streamlit_cytoscape/frontend/build/32b01d6a21d9433a251c.ttf
streamlit_cytoscape/frontend/build/apache-arrow.a539a5777ad256e7dd24.bundle.js
streamlit_cytoscape/frontend/build/cytoscape.ea5b6f4c4d23c592caab.bundle.js
streamlit_cytoscape/frontend/build/cytoscape.ea5b6f4c4d23c592caab.bundle.js.LICENSE.txt
streamlit_cytoscape/frontend/build/icons/account_balance.svg
streamlit_cytoscape/frontend/build/icons/alternate_email.svg
streamlit_cytoscape/frontend/build/icons/analytics.svg
streamlit_cytoscape/frontend/build/icons/assured_workload.svg
streamlit_cytoscape/frontend/build/icons/badge.svg
streamlit_cytoscape/frontend/build/icons/business.svg
streamlit_cytoscape/frontend/build/icons/campaign.svg
streamlit_cytoscape/frontend/build/icons/cell_tower.svg
streamlit_cytoscape/frontend/build/icons/chat.svg
streamlit_cytoscape/frontend/build/icons/cloud.svg
streamlit_cytoscape/frontend/build/icons/credit_card.svg
streamlit_cytoscape/frontend/build/icons/description.svg
streamlit_cytoscape/frontend/build/icons/directions_car.svg
streamlit_cytoscape/frontend/build/icons/dns.svg
streamlit_cytoscape/frontend/build/icons/email.svg
streamlit_cytoscape/frontend/build/icons/factory.svg
streamlit_cytoscape/frontend/build/icons/flag.svg
streamlit_cytoscape/frontend/build/icons/flight.svg
streamlit_cytoscape/frontend/build/icons/folder.svg
streamlit_cytoscape/frontend/build/icons/group.svg
streamlit_cytoscape/frontend/build/icons/home.svg
streamlit_cytoscape/frontend/build/icons/inventory.svg
streamlit_cytoscape/frontend/build/icons/key.svg
streamlit_cytoscape/frontend/build/icons/language.svg
streamlit_cytoscape/frontend/build/icons/laptop.svg
streamlit_cytoscape/frontend/build/icons/link.svg
streamlit_cytoscape/frontend/build/icons/local_shipping.svg
streamlit_cytoscape/frontend/build/icons/lock.svg
streamlit_cytoscape-0.1.4.dist-info/METADATA
streamlit_cytoscape-0.1.4.dist-info/WHEEL
streamlit_cytoscape-0.1.4.dist-info/licenses/LICENSE
streamlit_cytoscape-0.1.4.dist-info/RECORD
