Metadata-Version: 2.4
Name: streamlit-cytoscape
Version: 0.1.4
Summary: A flexible, customizable, Streamlit component for interactive graph visualization using Cytoscape.js
License: MIT
License-File: LICENSE
Author: Natalie Gill
Requires-Python: >=3.10,<4.0
Classifier: License :: OSI Approved :: MIT License
Classifier: Programming Language :: Python :: 3
Classifier: Programming Language :: Python :: 3.10
Classifier: Programming Language :: Python :: 3.11
Classifier: Programming Language :: Python :: 3.12
Classifier: Programming Language :: Python :: 3.13
Classifier: Programming Language :: Python :: 3.14
Requires-Dist: streamlit (>=0.63)
